catbus/__init__.py
catbus/catbus.py
catbus/catbustypes.py
catbus/client.py
catbus/data_structures.py
catbus/database.py
catbus/directory.py
catbus/logger.py
catbus/messages.py
catbus/options.py
catbus/server.py
catbus/test.py
catbus-1.0.2.dist-info/DESCRIPTION.rst
catbus-1.0.2.dist-info/METADATA
catbus-1.0.2.dist-info/RECORD
catbus-1.0.2.dist-info/WHEEL
catbus-1.0.2.dist-info/entry_points.txt
catbus-1.0.2.dist-info/metadata.json
catbus-1.0.2.dist-info/top_level.txt
