Metadata-Version: 2.0
Name: catbus
Version: 1.0.2
Summary: Catbus
Home-page: UNKNOWN
Author: UNKNOWN
Author-email: UNKNOWN
License: GNU General Public License v3
Platform: UNKNOWN
Requires-Dist: click (>=6.6)
Requires-Dist: crcmod (==1.7)
Requires-Dist: elysianfields (>=1.0)
Requires-Dist: fnvhash (==0.1.0)
Requires-Dist: netifaces (==0.10.6)
Requires-Dist: sapphire (>=1.0.2)
